Metadata-Version: 2.4
Name: npynuma
Version: 0.1.0
Summary: Allocate numpy arrays on NUMA nodes
Author-email: xsgeng <xsgeng@siom.ac.cn>
License: Copyright (c) 2025 xsgeng.
Project-URL: Homepage, https://github.com/xsgeng/npynuma
Classifier: Development Status :: 3 - Alpha
Classifier: Intended Audience :: Science/Research
Classifier: Programming Language :: Python :: 3
Classifier: Operating System :: POSIX :: Linux
License-File: LICENSE
Requires-Dist: numpy>=1.22
Dynamic: license-file
